{
	"observer": {
        "0": [
            90,
            0,
            0
        ],
        "1": [
            270,
            0,
            0
        ],
        "2": [
            0,
            0,
            0
        ],
        "3": [
            0,
            180,
            0
        ],
        "4": [
            0,
            270,
            0
        ],
        "5": [
            0,
            90,
            0
        ]
    },
	"cross_texture":{
		"None":[0,45,0],
		"0":[0,45,0],
		"1":[0,45,0],
		"2":[0,45,0],
		"3":[0,45,0],
		"4":[0,45,0],
		"5":[0,45,0],
		"6":[0,45,0]
	},
    "facing_block": {
        "0": [
            90,
            0,
            0
        ],
        "1": [
            270,
            0,
            0
        ],
        "2": [
            0,
            0,
            0
        ],
        "3": [
            0,
            180,
            0
        ],
        "4": [
            0,
            270,
            0
        ],
        "5": [
            0,
            90,
            0
        ]
    },
    "dispenser": {
        "0": [
            270,
            0,
            0
        ],
        "1": [
            90,
            0,
            0
        ],
        "2": [
            0,
            180,
            0
        ],
        "3": [
            0,
            0,
            0
        ],
        "4": [
            0,
            90,
            0
        ],
        "5": [
            0,
            270,
            0
        ]
    },
    "piston": {
        "0": [
            180,
            0,
            0
        ],
        "1": [
            0,
            0,
            0
        ],
        "2": [
            -90,
            0,
            0
        ],
        "3": [
            90,
            0,
            0
        ],
        "4": [
            0,
            0,
            -90
        ],
        "5": [
            0,
            0,
            90
        ]
    },
	"sticky_piston": {
        "0": [
            180,
            0,
            0
        ],
        "1": [
            0,
            0,
            0
        ],
        "2": [
            -90,
            0,
            0
        ],
        "3": [
            90,
            0,
            0
        ],
        "4": [
            0,
            0,
            -90
        ],
        "5": [
            0,
            0,
            90
        ]
    },
    "furnace": {
        "0": [
            180,
            0,
            0
        ],
        "1": [
            0,
            0,
            0
        ],
        "2": [
            0,
            180,
            0
        ],
        "3": [
            0,
            0,
            0
        ],
        "4": [
            0,
            90,
            0
        ],
        "5": [
            0,
            -90,
            0
        ]
    },
    "repeater": {
        "0": [0,180,0],
        "1": [0,-90,0],
        "2": [0,0,0],
        "3": [0,90,0]
    },
    "comparator": {
        "0": [
            0,
            180,
            0
        ],
        "1": [
            0,
            -90,
            0
        ],
        "2": [
            0,
            0,
            0
        ],
        "3": [
            0,
            90,
            0
        ]
    },
    "torch": {
        "top": [
            0,
            0,
            0
        ],
        "north": [
            -45,
            0,
            0
        ],
        "south": [
            45,
            0,
            0
        ],
        "east": [
            0,
            0,
            45
        ],
        "west": [
            0,
            0,
            -45
        ]
    },
	"stairs":{
        "0": [
            0,
            90,
            0
        ],
        "1": [
            0,
            -90,
            0
        ],
        "2": [
            0,
            180,
            0
        ],
        "3": [
            0,
            0,
            0
        ]
    },
	"frame":{
		"0": [
            180,
            0,
            0
        ],
		"1": [
            0,
            0,
            0
        ],
		"2": [
            90,
            0,
            0
        ],
		"3": [
            -90,
            0,
            0
        ],
		"4": [
            0,
            0,
            90
        ],
		"5": [
            0,
            0,
            -90
        ]
	},
	"button":{
		"0": [
            180,
            0,
            0
        ],
		"1": [
            0,
            0,
            0
        ],
		"2": [
            90,
            0,
            0
        ],
		"3": [
            -90,
            0,
            0
        ],
		"4": [
            0,
            90,
            90
        ],
		"5": [
            0,
            90,
            -90
        ]
	},
	"hopper":{
        "0": [
            0,
            0,
            0
        ],
        "1": [
             0,
            90,
            0
        ],
        "2": [
            0,
            270,
            0
        ],
        "3": [
            0,
            90,
            0
        ],
        "4": [
            0,
            180,
            0
        ],
        "5": [
            0,
            0,
            0
        ]
    },
	
	"end_rod":{
		"0":[180,0,0],
		"1":[0,0,0],
		"2":[270,0,0],
		"3":[90,0,0],
		"4":[0,0,270],
		"5":[0,0,90]
	},
    "trapdoor": {
        "0": [
            0,
            -90,
            0
        ],
        "1": [
            0,
            90,
            0
        ],
        "2": [
            0,
            0,
            0
        ],
        "3": [
            0,
            180,
            0
        ]
    },
	    "door": {
        "0": [
            0,
            -90,
            0
        ],
        "2": [
            0,
            90,
            0
        ],
        "1": [
            0,
            0,
            0
        ],
        "3": [
            0,
            180,
            0
        ]
    },
	    "standing_sign": {
        "0": [
            0,
            0,
            0
        ],
        "1": [
            0,
            22.5,
            0
        ],
        "2": [
            0,
            45,
            0
        ],
        "3": [
            0,
            67.5,
            0
        ],
        "4": [
            0,
            90,
            0
        ],
        "5": [
            0,
            112.5,
            0
        ],
        "6": [
            0,
            135,
            0
        ],
        "7": [
            0,
            157.5,
            0
        ],
        "8": [
            0,
            180,
            0
        ],
        "9": [
            0,
            202.5,
            0
        ],
        "10": [
            0,
            225,
            0
        ],
        "11": [
            0,
            247.5,
            0
        ],
        "12": [
            0,
            270,
            0
        ],
        "13": [
            0,
            292.5,
            0
        ],
        "14": [
            0,
            315,
            0
        ],
        "15": [
            0,
            337.5,
            0
        ]
    },
	"wall_sign": {
        "0": [
            0,
            0,
            0
        ],
        "1": [
            0,
            22.5,
            0
        ],
        "2": [
            0,
            45,
            0
        ],
        "3": [
            0,
            67.5,
            0
        ],
        "4": [
            0,
            90,
            0
        ],
        "5": [
            0,
            112.5,
            0
        ],
        "6": [
            0,
            135,
            0
        ],
        "7": [
            0,
            157.5,
            0
        ],
        "8": [
            0,
            180,
            0
        ],
        "9": [
            0,
            202.5,
            0
        ],
        "10": [
            0,
            225,
            0
        ],
        "11": [
            0,
            247.5,
            0
        ],
        "12": [
            0,
            270,
            0
        ],
        "13": [
            0,
            292.5,
            0
        ],
        "14": [
            0,
            315,
            0
        ],
        "15": [
            0,
            337.5,
            0
        ]
    }
}